edc_pylabels/__init__.py
edc_pylabels/actions.py
edc_pylabels/admin_site.py
edc_pylabels/apps.py
edc_pylabels/auth_objects.py
edc_pylabels/auths.py
edc_pylabels/drawing_callable_example.py
edc_pylabels/label_configs.py
edc_pylabels/site_label_configs.py
edc_pylabels/urls.py
edc_pylabels/admin/__init__.py
edc_pylabels/admin/label_configuration_admin.py
edc_pylabels/admin/label_specification_admin.py
edc_pylabels/forms/__init__.py
edc_pylabels/forms/label_configuration_form.py
edc_pylabels/migrations/0001_initial.py
edc_pylabels/migrations/0002_alter_label_options_label_created_and_more.py
edc_pylabels/migrations/0003_label_sample_data.py
edc_pylabels/migrations/0004_remove_label_drawing_callable_name_and_more.py
edc_pylabels/migrations/0005_labelconfiguration_delete_label_and_more.py
edc_pylabels/migrations/0006_delete_drawing.py
edc_pylabels/migrations/0007_alter_labelconfiguration_name.py
edc_pylabels/migrations/0008_labelconfiguration_requires_allocated.py
edc_pylabels/migrations/0009_remove_labelconfiguration_requires_allocated_and_more.py
edc_pylabels/migrations/0010_alter_labelconfiguration_requires_allocation.py
edc_pylabels/migrations/0011_alter_labelconfiguration_name.py
edc_pylabels/migrations/__init__.py
edc_pylabels/models/__init__.py
edc_pylabels/models/label_configuration.py
edc_pylabels/models/label_specification_proxy.py
edc_pylabels/tests/__init__.py
edc_pylabels/tests/test_settings.py
edc_pylabels/tests/tests/__init__.py
edc_pylabels/tests/tests/test_pylabel.py
edc_pylabels-1.0.1.dist-info/licenses/AUTHORS
edc_pylabels-1.0.1.dist-info/licenses/LICENSE
edc_pylabels-1.0.1.dist-info/METADATA
edc_pylabels-1.0.1.dist-info/WHEEL
edc_pylabels-1.0.1.dist-info/top_level.txt
edc_pylabels-1.0.1.dist-info/RECORD
