Metadata-Version: 2.4
Name: edc-pylabels
Version: 1.0.1
Summary: Project to integrate django-pylabels into clinicedc/edc projects
Author-email: Erik van Widenfelt <ew2789@gmail.com>
License:                     GNU GENERAL PUBLIC LICENSE
Keywords: Django clinic/edc EDC avery pylabels
Classifier: Development Status :: 5 - Production/Stable
Classifier: License :: OSI Approved :: GNU General Public License v3 or later (GPLv3+)
Classifier: Operating System :: OS Independent
Classifier: Programming Language :: Python
Requires-Python: >=3.12
License-File: LICENSE
License-File: AUTHORS
Requires-Dist: django-pylabels
Dynamic: license-file
